odoo9_addon_website_container_fluid-9.0.1.0.0-py2.7-nspkg.pth
odoo_addons/website_container_fluid/__openerp__.py
odoo_addons/website_container_fluid/__init__.py
odoo_addons/website_container_fluid/README.rst
odoo_addons/website_container_fluid/templates/snippets.xml
odoo_addons/website_container_fluid/i18n/ru.po
odoo_addons/website_container_fluid/i18n/it.po
odoo_addons/website_container_fluid/i18n/es.po
odoo_addons/website_container_fluid/i18n/bg.po
odoo_addons/website_container_fluid/i18n/sl.po
odoo_addons/website_container_fluid/i18n/de.po
odoo_addons/website_container_fluid/i18n/fr.po
odoo_addons/website_container_fluid/i18n/pt_BR.po
odoo_addons/website_container_fluid/i18n/el_GR.po
odoo_addons/website_container_fluid/demo/pages.xml
odoo_addons/website_container_fluid/static/description/icon.png
odoo9_addon_website_container_fluid-9.0.1.0.0.dist-info/top_level.txt
odoo9_addon_website_container_fluid-9.0.1.0.0.dist-info/WHEEL
odoo9_addon_website_container_fluid-9.0.1.0.0.dist-info/RECORD
odoo9_addon_website_container_fluid-9.0.1.0.0.dist-info/metadata.json
odoo9_addon_website_container_fluid-9.0.1.0.0.dist-info/DESCRIPTION.rst
odoo9_addon_website_container_fluid-9.0.1.0.0.dist-info/METADATA
odoo9_addon_website_container_fluid-9.0.1.0.0.dist-info/namespace_packages.txt
